rtcm/__init__.py
rtcm/rtcmDecoder.py
rtcm/clients/ntripClient.py
rtcm/clients/receiverClient.py
rtcm/dataProcessing/CSVWriter.py
rtcm/dataProcessing/sourceParser.py
rtcm/decoder/MSM7Decoder.py
rtcm/decoder/ephemerisDecoder.py
rtcm/utils/__init__.py
rtcm/utils/argumentParser.py
rtcm/utils/dict.py
rtcm/utils/constants/CSVHeaders.pkl
rtcm/utils/constants/GNSSCodes.pkl
rtcm/utils/constants/dataFields.pkl
rtcm/utils/constants/sigID.pkl
rtcmdecoder-1.0.dist-info/LICENSE.txt
rtcmdecoder-1.0.dist-info/METADATA
rtcmdecoder-1.0.dist-info/WHEEL
rtcmdecoder-1.0.dist-info/entry_points.txt
rtcmdecoder-1.0.dist-info/top_level.txt
rtcmdecoder-1.0.dist-info/RECORD
