Metadata-Version: 2.1
Name: rtcmdecoder
Version: 1.0
Summary: A RTCM decoder for MSM7 and ephemerides data in Python
Author-email: "Matthias Vancanneyt, Nathan Prakopetz, Ruben Callens" <nathan.prakopetz@pm.me>
Project-URL: Homepage, https://github.com/P3tzl/Project-SE426
Classifier: Programming Language :: Python :: 3
Classifier: License :: OSI Approved :: MIT License
Classifier: Operating System :: OS Independent
Requires-Python: >=3.10.6
License-File: LICENSE.txt
Requires-Dist: alive-progress (>=3.1.1)
Requires-Dist: numpy (>=1.24.3)
Requires-Dist: pandas (>=2.0.1)
Requires-Dist: pyrtcm (>=1.0.8)
Requires-Dist: pyserial (>=3.5)
